{"textures":{"0":"modelengine:entity/rlgl"},"elements":[{"name":"cube","from":[5.212132,-0.23933911,6.8],"to":[7.612132,2.7606611,9.8],"rotation":{"angle":45,"axis":"x","origin":[6.112132,1.260661,8.3]},"faces":{"down":{"uv":[9.5,8.25,10,8.875],"rotation":0,"texture":"#0","tintindex":0},"east":{"uv":[0.625,9.25,0,9.875],"rotation":0,"texture":"#0","tintindex":0},"north":{"uv":[10,1.25,9.5,1.875],"rotation":0,"texture":"#0","tintindex":0},"south":{"uv":[10,1.875,9.5,2.5],"rotation":0,"texture":"#0","tintindex":0},"up":{"uv":[9.5,8.25,10,7.625],"rotation":0,"texture":"#0","tintindex":0},"west":{"uv":[7.125,9.125,6.5,9.75],"rotation":0,"texture":"#0","tintindex":0}}},{"name":"cube","from":[4.912132,1.860661,6.2],"to":[7.912132,5.460661,9.8],"rotation":{"angle":0,"axis":"x","origin":[3.7121317,-24.539341,8]},"faces":{"down":{"uv":[9.125,2.5,9.75,3.25],"rotation":0,"texture":"#0","tintindex":0},"east":{"uv":[9.25,7,8.5,7.75],"rotation":0,"texture":"#0","tintindex":0},"north":{"uv":[9.5,8.5,8.875,9.25],"rotation":0,"texture":"#0","tintindex":0},"south":{"uv":[9.625,6.25,9,7],"rotation":0,"texture":"#0","tintindex":0},"up":{"uv":[2.5,9.875,3.125,9.125],"rotation":0,"texture":"#0","tintindex":0},"west":{"uv":[4,8.5,3.25,9.25],"rotation":0,"texture":"#0","tintindex":0}}},{"name":"cube","from":[4.612132,5.460661,5.8999996],"to":[8.212132,10.260662,10.1],"rotation":{"angle":0,"axis":"x","origin":[4.0121317,-18.539341,7.7]},"faces":{"down":{"uv":[8.125,8,8.875,8.875],"rotation":0,"texture":"#0","tintindex":0},"east":{"uv":[7.375,7.25,6.5,8.25],"rotation":0,"texture":"#0","tintindex":0},"north":{"uv":[5.25,7.75,4.5,8.75],"rotation":0,"texture":"#0","tintindex":0},"south":{"uv":[6,7.75,5.25,8.75],"rotation":0,"texture":"#0","tintindex":0},"up":{"uv":[7.375,8.875,8.125,8],"rotation":0,"texture":"#0","tintindex":0},"west":{"uv":[3.375,7.25,2.5,8.25],"rotation":0,"texture":"#0","tintindex":0}}}],"display":{"head":{"translation":[0,-6.4,0],"rotation":[0,0,0],"scale":[3.8095,3.8095,3.8095]}}}
